hsbg_sim.cp39-win_amd64.pyd
hsbg_sim-1.0.0.dist-info/LICENSE
hsbg_sim-1.0.0.dist-info/METADATA
hsbg_sim-1.0.0.dist-info/WHEEL
hsbg_sim-1.0.0.dist-info/top_level.txt
hsbg_sim-1.0.0.dist-info/RECORD
