Metadata-Version: 2.1
Name: hsbg-sim
Version: 1.0.0
Summary: Python interface for the Hearthstone Battlegrounds combat simulator.
Home-page: https://github.com/galacticglum/hearthstone-battlegrounds-simulator/
Author: Shon Verch
Author-email: verchshon@gmail.com
License: UNKNOWN
Platform: UNKNOWN
Classifier: Programming Language :: Python :: 3
Classifier: License :: OSI Approved :: MIT License
Classifier: Operating System :: OS Independent
Requires-Python: >=3.6
